README.md
setup.py
rtfraptor/__init__.py
rtfraptor/app.py
rtfraptor/engine.py
rtfraptor/utils.py
rtfraptor.egg-info/PKG-INFO
rtfraptor.egg-info/SOURCES.txt
rtfraptor.egg-info/dependency_links.txt
rtfraptor.egg-info/entry_points.txt
rtfraptor.egg-info/requires.txt
rtfraptor.egg-info/top_level.txt