Metadata-Version: 2.1
Name: rtfraptor
Version: 1.0.0
Summary: Dump interesting OLE parts from RTF documents by instrumenting Word
Home-page: https://github.com/edeca/rtfraptor
Author: David Cannings
Author-email: david@edeca.net
License: GNU Affero General Public License v3
Platform: UNKNOWN
Classifier: Programming Language :: Python :: 2
Classifier: License :: OSI Approved :: GNU Affero General Public License v3
Classifier: Environment :: Win32 (MS Windows)
Classifier: Operating System :: Microsoft :: Windows
Classifier: Development Status :: 4 - Beta
